fastapi_assets/__init__.py
fastapi_assets/core/__init__.py
fastapi_assets/core/base_validator.py
fastapi_assets/core/exceptions.py
fastapi_assets/request_validators/__init__.py
fastapi_assets/request_validators/cookie_validator.py
fastapi_assets/request_validators/header_validator.py
fastapi_assets/request_validators/path_validator.py
fastapi_assets/request_validators/query_validator.py
fastapi_assets/validators/__init__.py
fastapi_assets/validators/csv_validator.py
fastapi_assets/validators/file_validator.py
fastapi_assets/validators/image_validator.py
fastapi_assets/validators/utils.py
fastapi_assets-0.1.0.dist-info/licenses/LICENSE.txt
fastapi_assets-0.1.0.dist-info/METADATA
fastapi_assets-0.1.0.dist-info/WHEEL
fastapi_assets-0.1.0.dist-info/top_level.txt
fastapi_assets-0.1.0.dist-info/RECORD
