Metadata-Version: 2.4
Name: fastapi-assets
Version: 0.1.0
Summary: FastAPI Assets - A validation and assertion toolkit for FastAPI file uploads and request metadata.
Author-email: Fastapi-Assets Development Team <openvergecommunity@gmail.com>
License-Expression: MIT
Project-URL: Homepage, https://github.com/OpenVerge/fastapi-assets
Project-URL: Docs, https://openverge.github.io/fastapi-assets/
Requires-Python: >=3.10
License-File: LICENSE.txt
Requires-Dist: fastapi==0.115.0
Provides-Extra: pandas
Requires-Dist: pandas==2.3.3; extra == "pandas"
Provides-Extra: image
Requires-Dist: pillow==12.0.0; extra == "image"
Provides-Extra: dev
Requires-Dist: anyio>=4.11.0; extra == "dev"
Requires-Dist: httpx>=0.28.1; extra == "dev"
Requires-Dist: mkdocs>=1.6.1; extra == "dev"
Requires-Dist: mkdocs-material>=9.7.0; extra == "dev"
Requires-Dist: mkdocstrings[python]>=0.30.1; extra == "dev"
Requires-Dist: mypy>=1.18.2; extra == "dev"
Requires-Dist: pytest>=9.0.0; extra == "dev"
Requires-Dist: pytest-asyncio>=1.3.0; extra == "dev"
Requires-Dist: ruff>=0.14.4; extra == "dev"
Requires-Dist: tox>=4.32.0; extra == "dev"
Requires-Dist: tox-uv>=1.29.0; extra == "dev"
Provides-Extra: optional
Requires-Dist: fastapi-assets[pandas]; extra == "optional"
Requires-Dist: fastapi-assets[image]; extra == "optional"
Dynamic: license-file
